eric_tools/Abstract.py
eric_tools/__init__.py
eric_tools/async_queue.py
eric_tools/convert_json.py
eric_tools/decorator.py
eric_tools/delete_duplicate.py
eric_tools/downloader.py
eric_tools/dynamic_settings.py
eric_tools/encryption_classmethod.py
eric_tools/excel_generator.py
eric_tools/exception_class.py
eric_tools/jwt_encrypt.py
eric_tools/logMixin.py
eric_tools/logger.py
eric_tools/pgsql.py
eric_tools/resize_image.py
eric_tools-1.4.0.dist-info/LICENSE
eric_tools-1.4.0.dist-info/METADATA
eric_tools-1.4.0.dist-info/WHEEL
eric_tools-1.4.0.dist-info/top_level.txt
eric_tools-1.4.0.dist-info/RECORD
