Metadata-Version: 2.1
Name: eric-tools
Version: 1.4.0
Summary: Python Daily Development Tools
Home-page: https://github.com/Eric-jxl/Tools
Author: Eric
Author-email: jxleric95@gmail.com
License: UNKNOWN
Platform: UNKNOWN
Classifier: Programming Language :: Python :: 3
Classifier: License :: OSI Approved :: MIT License
Classifier: Operating System :: OS Independent
Requires-Python: >=3.0
License-File: LICENSE
Requires-Dist: psycopg2
Requires-Dist: requests
Requires-Dist: Pillow
Requires-Dist: xlsxwriter
Requires-Dist: ImageHash
